burgeon/__init__.py
burgeon/main.py
burgeon-0.1.3.dist-info/LICENSE
burgeon-0.1.3.dist-info/WHEEL
burgeon-0.1.3.dist-info/METADATA
burgeon-0.1.3.dist-info/RECORD
