Metadata-Version: 2.1
Name: burgeon
Version: 0.1.3
Summary: 
License: Apache-2.0
Author: Uriel Mandujano
Author-email: uriel.mandujano14@gmail.com
Requires-Python: >=3.6.2,<4.0.0
Classifier: License :: OSI Approved :: Apache Software License
Classifier: Programming Language :: Python :: 3
Classifier: Programming Language :: Python :: 3.10
Classifier: Programming Language :: Python :: 3.7
Classifier: Programming Language :: Python :: 3.8
Classifier: Programming Language :: Python :: 3.9
Requires-Dist: watchgod (>=0.7,<0.8)
